langchain_parallel/__init__.py
langchain_parallel/_client.py
langchain_parallel/_types.py
langchain_parallel/chat_models.py
langchain_parallel/extract_tool.py
langchain_parallel/py.typed
langchain_parallel/search_tool.py
langchain_parallel-0.1.0.dist-info/LICENSE
langchain_parallel-0.1.0.dist-info/METADATA
langchain_parallel-0.1.0.dist-info/WHEEL
langchain_parallel-0.1.0.dist-info/RECORD
