Metadata-Version: 2.3
Name: langchain-parallel
Version: 0.1.0
Summary: A LangChain integration for Parallel Web AI services, including Chat and Search.
Home-page: https://github.com/parallel-web/langchain-parallel
License: MIT
Author: Parallel Team
Author-email: support@parallel.ai
Requires-Python: >=3.9,<4.0
Classifier: License :: OSI Approved :: MIT License
Classifier: Programming Language :: Python :: 3
Classifier: Programming Language :: Python :: 3.9
Classifier: Programming Language :: Python :: 3.10
Classifier: Programming Language :: Python :: 3.11
Classifier: Programming Language :: Python :: 3.12
Classifier: Programming Language :: Python :: 3.13
Requires-Dist: httpx (>=0.27.0,<0.28.0)
Requires-Dist: langchain-core (>=0.3.76,<0.4.0)
Requires-Dist: openai (>=1.88.0,<2.0.0)
Requires-Dist: parallel-web (>=0.3.3,<0.4.0)
Requires-Dist: pydantic (>=2.11.7,<3.0.0)
Project-URL: Repository, https://github.com/parallel-web/langchain-parallel
Project-URL: Release Notes, https://github.com/parallel-web/langchain-parallel/releases
Project-URL: Source Code, https://github.com/parallel-web/langchain-parallel
